Telegrams/__init__.py
Telegrams/exceptions/__init__.py
Telegrams/exceptions/exceptions.py
Telegrams/functions/__init__.py
Telegrams/functions/function01.py
Telegrams/functions/function02.py
Telegrams/functions/function03.py
telegrams-0.0.4.dist-info/METADATA
telegrams-0.0.4.dist-info/WHEEL
telegrams-0.0.4.dist-info/top_level.txt
telegrams-0.0.4.dist-info/RECORD
